<?xml version="1.0" encoding="UTF-8"?>
<data>
    <female>
        <feature gen="SF">151</feature>
        <feature gen="MF">11</feature>
        <feature gen="N">25</feature>
        <feature gen="MMN">43</feature>
        <feature gen="SM">29</feature>
    </female>
     <male>
            <feature gen="SF">9</feature>
            <feature gen="MF">4</feature>
            <feature gen="N">25</feature>
            <feature gen="MMN">57</feature>
            <feature gen="SM">132</feature>
    </male>
</data>
